mlp_mixer_pytorch/__init__.py
mlp_mixer_pytorch/mlp_mixer_3d_pytorch.py
mlp_mixer_pytorch/mlp_mixer_pytorch.py
mlp_mixer_pytorch/permutator.py
mlp_mixer_pytorch-0.3.1.dist-info/licenses/LICENSE
mlp_mixer_pytorch-0.3.1.dist-info/METADATA
mlp_mixer_pytorch-0.3.1.dist-info/WHEEL
mlp_mixer_pytorch-0.3.1.dist-info/top_level.txt
mlp_mixer_pytorch-0.3.1.dist-info/RECORD
